<question type="stack">
    <name>
      <text>027) Quotientenregel</text>
    </name>
    <questiontext format="html">
      <text>&lt;p&gt;Bestimmen Sie die erste Ableitung der folgenden Funktion mit Hilfe der Quotientenregel&lt;br&gt;&lt;/p&gt;&lt;div class="editor-indent" style="margin-left: 30px;"&gt;&lt;p style=""&gt;&amp;nbsp;\( f(t)= \dfrac{t^{@A@}}{{@B@}\cdot e^{t}} \)&lt;/p&gt;&lt;p style=""&gt;&lt;br&gt;&lt;/p&gt;&lt;p style=""&gt;\(f'(t)=\) [[input:ans1]] [[validation:ans1]] [[feedback:prt1]]&lt;/p&gt;&lt;/div&gt;</text>
    </questiontext>
    <generalfeedback format="html">
      <text>&lt;h4&gt;&lt;strong&gt;Lösung&lt;/strong&gt;&lt;/h4&gt;&lt;p&gt;&lt;br&gt;&lt;/p&gt;&lt;p&gt;\(f(t)= \dfrac{t^{@A@}}{{@B@}\cdot e^{t}}\)&lt;br&gt;&lt;/p&gt;&lt;p&gt;&lt;br&gt;&lt;/p&gt;&lt;p&gt;Sei \(u(t)=t^{@A@}\) mit \(u^{\prime}(t)={@A@}t^{@A-1@}\)&lt;/p&gt;&lt;p&gt;und \(v(t)={@B@}e^{t}\) mit \(v^{\prime}(t)={@B@}e^t\)&lt;/p&gt;&lt;p&gt;&lt;br&gt;&lt;/p&gt;&lt;p&gt;Mit&amp;nbsp;&lt;/p&gt;&lt;p&gt;\(f(t)=\dfrac{u(t)}{v(t)}=\dfrac{t^{@A@}}{{@B@}e^{t}}\)&lt;/p&gt;&lt;p&gt;&lt;br&gt;&lt;/p&gt;&lt;p&gt;und&amp;nbsp;der Quotientenregel folgt&lt;/p&gt;&lt;p&gt;&lt;br&gt;&lt;/p&gt;&lt;p&gt;\(f^{\prime}(t)=\dfrac{u^{\prime}(t)v(t)-u(t)v^{\prime}(t)}{v(t)^2}\)&lt;/p&gt;&lt;p&gt;&lt;br&gt;&lt;/p&gt;&lt;p&gt;&amp;nbsp; &amp;nbsp; &amp;nbsp; &amp;nbsp; &amp;nbsp; &amp;nbsp;\(=\dfrac{{@A@}t^{@A-1@}\cdot{@B@}e^{t}-t^{@A@}\cdot{@B@}e^{t}}{{@B^2@}e^{2t}}\)&amp;nbsp; &amp;nbsp; &amp;nbsp; &amp;nbsp; &amp;nbsp;|Mit \({@B@}\) kürzen und zusammenfassen&lt;/p&gt;&lt;p&gt;&lt;br&gt;&lt;/p&gt;&lt;p&gt;&amp;nbsp; &amp;nbsp; &amp;nbsp; &amp;nbsp; &amp;nbsp; &amp;nbsp;\(=\dfrac{({@A@}t^{@A-1@}-t^{@A@})e^{t}}{{@B@}e^{2t}}\)&amp;nbsp; &amp;nbsp; &amp;nbsp; &amp;nbsp; &amp;nbsp; &amp;nbsp; &amp;nbsp; &amp;nbsp; &amp;nbsp; &amp;nbsp;|Mit \(\dfrac{e^t}{e^{2t}}=e^te^{-2t}=e^{t-2t}=e^{-t}\)&lt;/p&gt;&lt;p&gt;&amp;nbsp;&amp;nbsp;&lt;/p&gt;&lt;p&gt;&amp;nbsp; &amp;nbsp; &amp;nbsp; &amp;nbsp; &amp;nbsp; \(=\frac{1}{{@B@}}({@A@}t^{@A-1@}-t^{@A@})e^{-t}\)&lt;/p&gt;</text>
    </generalfeedback>
    <defaultgrade>1.0000000</defaultgrade>
    <penalty>0.1000000</penalty>
    <hidden>0</hidden>
    <idnumber />
    <stackversion>
      <text>2020120600</text>
    </stackversion>
    <questionvariables>
      <text>A:2+rand(9);
B:2+rand(9);
Ableitung:diff(t^A/(B*exp(t)),t)</text>
    </questionvariables>
    <specificfeedback format="html">
      <text />
    </specificfeedback>
    <questionnote>
      <text>n</text>
    </questionnote>
    <questionsimplify>1</questionsimplify>
    <assumepositive>0</assumepositive>
    <assumereal>0</assumereal>
    <prtcorrect format="html">
      <text>Richtige Antwort, gut gemacht!</text>
    </prtcorrect>
    <prtpartiallycorrect format="html">
      <text>Ihre Antwort ist teilweise korrekt.</text>
    </prtpartiallycorrect>
    <prtincorrect format="html">
      <text>Falsche Antwort.</text>
    </prtincorrect>
    <multiplicationsign>dot</multiplicationsign>
    <sqrtsign>1</sqrtsign>
    <complexno>i</complexno>
    <inversetrig>cos-1</inversetrig>
    <logicsymbol>lang</logicsymbol>
    <matrixparens>[</matrixparens>
    <variantsselectionseed />
    <input>
      <name>ans1</name>
      <type>algebraic</type>
      <tans>Ableitung</tans>
      <boxsize>20</boxsize>
      <strictsyntax>1</strictsyntax>
      <insertstars>0</insertstars>
      <syntaxhint />
      <syntaxattribute>0</syntaxattribute>
      <forbidwords />
      <allowwords />
      <forbidfloat>1</forbidfloat>
      <requirelowestterms>0</requirelowestterms>
      <checkanswertype>0</checkanswertype>
      <mustverify>1</mustverify>
      <showvalidation>1</showvalidation>
      <options />
    </input>
    <prt>
      <name>prt1</name>
      <value>1.0000000</value>
      <autosimplify>1</autosimplify>
      <feedbackstyle>1</feedbackstyle>
      <feedbackvariables>
        <text />
      </feedbackvariables>
      <node>
        <name>0</name>
        <answertest>AlgEquiv</answertest>
        <sans>ans1</sans>
        <tans>Ableitung</tans>
        <testoptions />
        <quiet>0</quiet>
        <truescoremode>=</truescoremode>
        <truescore>1.0000000</truescore>
        <truepenalty />
        <truenextnode>-1</truenextnode>
        <trueanswernote>prt1-1-T</trueanswernote>
        <truefeedback format="html">
          <text />
        </truefeedback>
        <falsescoremode>=</falsescoremode>
        <falsescore>0.0000000</falsescore>
        <falsepenalty />
        <falsenextnode>-1</falsenextnode>
        <falseanswernote>prt1-1-F</falseanswernote>
        <falsefeedback format="html">
          <text />
        </falsefeedback>
      </node>
    </prt>
    <deployedseed>707801</deployedseed>
    <tags>
      <tag><text>getestet</text>
</tag>
      <tag><text>Übung</text>
</tag>
      <tag><text>Lösung</text>
</tag>
      <tag><text>Quotientenregel</text>
</tag>
    </tags>
  </question>

